AUTHORS.rst
CONTRIBUTING.rst
HISTORY.rst
LICENSE
MANIFEST.in
README.md
setup.cfg
setup.py
docs/Makefile
docs/authors.rst
docs/conf.py
docs/contributing.rst
docs/history.rst
docs/index.rst
docs/installation.rst
docs/make.bat
docs/readme.rst
docs/usage.rst
fastscape_litho/TA.py
fastscape_litho/__init__.py
fastscape_litho/_helper.py
fastscape_litho/_looper.py
fastscape_litho/fastscape_litho.py
fastscape_litho.egg-info/PKG-INFO
fastscape_litho.egg-info/SOURCES.txt
fastscape_litho.egg-info/dependency_links.txt
fastscape_litho.egg-info/not-zip-safe
fastscape_litho.egg-info/requires.txt
fastscape_litho.egg-info/top_level.txt
tests/__init__.py
tests/test_fastscape_litho.py