Metadata-Version: 2.1
Name: fastscape-litho
Version: 0.0.1
Summary: Feeding fastscape with a 3D bloc of differential lithology
Home-page: https://github.com/bgailleton/fastscape_litho
Author: Boris Gailleton
Author-email: boris.gailleton@gfz-potsdam.de
License: BSD license
Keywords: fastscape_litho
Platform: UNKNOWN
Classifier: Development Status :: 2 - Pre-Alpha
Classifier: Intended Audience :: Developers
Classifier: License :: OSI Approved :: BSD License
Classifier: Natural Language :: English
Classifier: Programming Language :: Python :: 3
Classifier: Programming Language :: Python :: 3.5
Classifier: Programming Language :: Python :: 3.6
Classifier: Programming Language :: Python :: 3.7
Classifier: Programming Language :: Python :: 3.8
Requires-Python: >=3.5
